MAA_PyQT5_messenger_server_app-0.0.4.data/scripts/server_run
server/__init__.py
server/server_app.py
server/common/__init__.py
server/common/decor_1.py
server/common/decor_2.py
server/common/descript.py
server/common/errors.py
server/common/meta_detect.py
server/common/utils.py
server/common/variables.py
server/decorator/__init__.py
server/decorator/decor.py
server/logs/__init__.py
server/logs/config_client_log.py
server/logs/config_log_2.py
server/logs/config_server_log.py
server/server/__init__.py
server/server/add_user.py
server/server/config_window.py
server/server/main_window.py
server/server/msg_processor.py
server/server/remove_user.py
server/server/server_base.py
server/server/server_gui.py
server/server/stat_window.py
MAA_PyQT5_messenger_server_app-0.0.4.dist-info/METADATA
MAA_PyQT5_messenger_server_app-0.0.4.dist-info/WHEEL
MAA_PyQT5_messenger_server_app-0.0.4.dist-info/top_level.txt
MAA_PyQT5_messenger_server_app-0.0.4.dist-info/RECORD
